trackingprotection_tools/DisconnectParser.py
trackingprotection_tools/DisconnectReporting.py
trackingprotection_tools/__init__.py
trackingprotection_tools/test/__init__.py
trackingprotection_tools/test/basetest.py
trackingprotection_tools/test/conftest.py
trackingprotection_tools/test/test_disconnect_parser.py
trackingprotection_tools/test/test_disconnect_reporting.py
trackingprotection_tools/test/utilities.py
trackingprotection_tools/test/resources/bad-mapping.json
trackingprotection_tools/test/resources/short-blocklist.json
trackingprotection_tools/test/resources/test-blocklist.json
trackingprotection_tools/test/resources/test-entitylist.json
trackingprotection_tools/test/resources/test-mapping.json
trackingprotection_tools/test/resources/unmapped-blocklist.json
trackingprotection_tools/test/resources/reports/add_comment.json
trackingprotection_tools/test/resources/reports/add_domain.json
trackingprotection_tools/test/resources/reports/add_observation.json
trackingprotection_tools-0.6.1.dist-info/LICENSE
trackingprotection_tools-0.6.1.dist-info/METADATA
trackingprotection_tools-0.6.1.dist-info/WHEEL
trackingprotection_tools-0.6.1.dist-info/top_level.txt
trackingprotection_tools-0.6.1.dist-info/RECORD
