Metadata-Version: 2.1
Name: trackingprotection-tools
Version: 0.6.1
Summary: Tools for working with Firefox Tracking Protection.
Home-page: https://github.com/mozilla/trackingprotection-tools
Author: Mozilla Corporation
Author-email: senglehardt@mozilla.com
License: MPL 2.0
Platform: UNKNOWN
Classifier: Environment :: Web Environment :: Mozilla
Classifier: Intended Audience :: Developers
Classifier: License :: OSI Approved :: Mozilla Public License 2.0 (MPL 2.0)
Classifier: Programming Language :: Python
Classifier: Programming Language :: Python :: 3
Classifier: Programming Language :: Python :: 3.6
Classifier: Programming Language :: Python :: 3.7
Classifier: Programming Language :: Python :: 3.8
Classifier: Topic :: Internet :: WWW/HTTP
Classifier: Topic :: Scientific/Engineering :: Information Analysis
Requires-Dist: domain-utils
Requires-Dist: requests
